pypodcaster/__init__.py
pypodcaster/__main__.py
pypodcaster/podcast.py
pypodcaster/templates/template.xml
pypodcaster-2.0.4.dist-info/DESCRIPTION.rst
pypodcaster-2.0.4.dist-info/METADATA
pypodcaster-2.0.4.dist-info/RECORD
pypodcaster-2.0.4.dist-info/WHEEL
pypodcaster-2.0.4.dist-info/entry_points.txt
pypodcaster-2.0.4.dist-info/metadata.json
pypodcaster-2.0.4.dist-info/top_level.txt
