Metadata-Version: 2.0
Name: pypodcaster
Version: 2.0.4
Summary: Generate podcast xml feed from a directory of media files
Home-page: http://github.com/mantlepro/pypodcaster
Author: mantlepro
Author-email: mantlepro@gmail.com
License: GPL-3.0
Platform: UNKNOWN
Requires-Dist: Jinja2
Requires-Dist: mutagen
Requires-Dist: pyyaml
Requires-Dist: validators
